setup.cfg
setup.py
timecheck/__init__.py
timecheck/cmdline.py
timecheck/timecheck.py
timecheck.egg-info/PKG-INFO
timecheck.egg-info/SOURCES.txt
timecheck.egg-info/dependency_links.txt
timecheck.egg-info/entry_points.txt
timecheck.egg-info/requires.txt
timecheck.egg-info/top_level.txt
timecheck/analyzer/__init__.py
timecheck/analyzer/analyze.py
timecheck/commands/__init__.py
timecheck/commands/analyze.py