Metadata-Version: 1.1
Name: timecheck
Version: 0.0.2
Summary: Easy and efficient way to gather time metrics for Python functions
Home-page: https://github.com/arpitbbhayani/timecheck
Author: Arpit Bhayani
Author-email: arpit.b.bhayani@gmail.com
License: UNKNOWN
Download-URL: https://github.com/arpitbbhayani/timecheck
Keywords: time,metrics
Platform: UNKNOWN
